pysxm/__init__.py
pysxm/ext.py
pysxm/pysxm.py
pysxm-1.5.0.dist-info/LICENSE
pysxm-1.5.0.dist-info/METADATA
pysxm-1.5.0.dist-info/WHEEL
pysxm-1.5.0.dist-info/RECORD
